odoo10_addon_web_export_view-10.0.1.0.0-py2.7-nspkg.pth
odoo10_addon_web_export_view-10.0.1.0.0.dist-info/top_level.txt
odoo10_addon_web_export_view-10.0.1.0.0.dist-info/WHEEL
odoo10_addon_web_export_view-10.0.1.0.0.dist-info/RECORD
odoo10_addon_web_export_view-10.0.1.0.0.dist-info/metadata.json
odoo10_addon_web_export_view-10.0.1.0.0.dist-info/DESCRIPTION.rst
odoo10_addon_web_export_view-10.0.1.0.0.dist-info/METADATA
odoo10_addon_web_export_view-10.0.1.0.0.dist-info/namespace_packages.txt
odoo/addons/web_export_view/__manifest__.py
odoo/addons/web_export_view/__init__.py
odoo/addons/web_export_view/README.rst
odoo/addons/web_export_view/i18n/zh_CN.po
odoo/addons/web_export_view/views/web_export_view_view.xml
odoo/addons/web_export_view/controllers/controllers.py
odoo/addons/web_export_view/controllers/__init__.py
odoo/addons/web_export_view/static/description/icon.png
odoo/addons/web_export_view/static/src/js/web_export_view.js
odoo/addons/web_export_view/static/src/xml/web_export_view_template.xml
