Metadata-Version: 2.0
Name: odoo10-addon-web-export-view
Version: 10.0.1.0.0
Summary: Web Export Current View
Home-page: http://www.agilebg.com
Author: Henry Zhou, Agile Business Group,             Odoo Community Association (OCA)
Author-email: support@odoo-community.org
License: AGPL-3
Platform: UNKNOWN
Requires-Dist: odoo (<10.1dev,>=10.0)
Classifier: Programming Language :: Python :: 2.7
Classifier: Framework :: Odoo
Classifier: License :: OSI Approved :: GNU Affero General Public License v3
